{"Adult Division 1": {"Boozehounds": "webcal://stats.sharksice.timetoscore.com/team-cal.php?team=4710&tlev=0&tseq=0&season=60&format=iCal", "Camels": "webcal://stats.sharksice.timetoscore.com/team-cal.php?team=4784&tlev=0&tseq=0&season=60&format=iCal", "Americans": "webcal://stats.sharksice.timetoscore.com/team-cal.php?team=323&tlev=0&tseq=0&season=60&format=iCal", "Pager Flakes": "webcal://stats.sharksice.timetoscore.com/team-cal.php?team=310&tlev=0&tseq=0&season=60&format=iCal"}, "Adult Division 2": {"Dung Beetle": "webcal://stats.sharksice.timetoscore.com/team-cal.php?team=215&tlev=0&tseq=0&season=60&format=iCal", "Battalion": "webcal://stats.sharksice.timetoscore.com/team-cal.php?team=2711&tlev=0&tseq=0&season=60&format=iCal", "Diablos": "webcal://stats.sharksice.timetoscore.com/team-cal.php?team=843&tlev=0&tseq=0&season=60&format=iCal"}, "Adult Division 3A": {"Devcon HC": "webcal://stats.sharksice.timetoscore.com/team-cal.php?team=4629&tlev=0&tseq=0&season=60&format=iCal", "Dragons": "webcal://stats.sharksice.timetoscore.com/team-cal.php?team=3762&tlev=0&tseq=0&season=60&format=iCal", "Marauders": "webcal://stats.sharksice.timetoscore.com/team-cal.php?team=4628&tlev=0&tseq=0&season=60&format=iCal", "Norcal Leafs": "webcal://stats.sharksice.timetoscore.com/team-cal.php?team=800&tlev=0&tseq=0&season=60&format=iCal", "Knights": "webcal://stats.sharksice.timetoscore.com/team-cal.php?team=4182&tlev=0&tseq=0&season=60&format=iCal"}, "Adult Division 3B": {"2nd Battalion": "webcal://stats.sharksice.timetoscore.com/team-cal.php?team=4684&tlev=0&tseq=0&season=60&format=iCal", "Time to Score": "webcal://stats.sharksice.timetoscore.com/team-cal.php?team=799&tlev=0&tseq=0&season=60&format=iCal", "TBD": "webcal://stats.sharksice.timetoscore.com/team-cal.php?team=4111&tlev=0&tseq=0&season=60&format=iCal", "Black Mambas": "webcal://stats.sharksice.timetoscore.com/team-cal.php?team=210&tlev=0&tseq=0&season=60&format=iCal"}, "Adult Division 4A": {"Beerhawks": "webcal://stats.sharksice.timetoscore.com/team-cal.php?team=569&tlev=0&tseq=0&season=60&format=iCal", "Mermen": "webcal://stats.sharksice.timetoscore.com/team-cal.php?team=2051&tlev=0&tseq=0&season=60&format=iCal", "Double Secret Probation": "webcal://stats.sharksice.timetoscore.com/team-cal.php?team=564&tlev=0&tseq=0&season=60&format=iCal", "OHC": "webcal://stats.sharksice.timetoscore.com/team-cal.php?team=38&tlev=0&tseq=0&season=60&format=iCal", "Shocker": "webcal://stats.sharksice.timetoscore.com/team-cal.php?team=633&tlev=0&tseq=0&season=60&format=iCal"}, "Adult Division 4B": {"Junkies": "webcal://stats.sharksice.timetoscore.com/team-cal.php?team=2613&tlev=0&tseq=0&season=60&format=iCal", "Ham Candle": "webcal://stats.sharksice.timetoscore.com/team-cal.php?team=4290&tlev=0&tseq=0&season=60&format=iCal", "Norcal Crossover": "webcal://stats.sharksice.timetoscore.com/team-cal.php?team=2601&tlev=0&tseq=0&season=60&format=iCal", "Money Shots": "webcal://stats.sharksice.timetoscore.com/team-cal.php?team=2955&tlev=0&tseq=0&season=60&format=iCal", "Good Guys": "webcal://stats.sharksice.timetoscore.com/team-cal.php?team=2953&tlev=0&tseq=0&season=60&format=iCal", "Misfits": "webcal://stats.sharksice.timetoscore.com/team-cal.php?team=55&tlev=0&tseq=0&season=60&format=iCal", "Pied Sniper": "webcal://stats.sharksice.timetoscore.com/team-cal.php?team=4638&tlev=0&tseq=0&season=60&format=iCal", "NVIDIA": "webcal://stats.sharksice.timetoscore.com/team-cal.php?team=340&tlev=0&tseq=0&season=60&format=iCal", "Southsiders": "webcal://stats.sharksice.timetoscore.com/team-cal.php?team=455&tlev=0&tseq=0&season=60&format=iCal", "K-Wings Supreme": "webcal://stats.sharksice.timetoscore.com/team-cal.php?team=4672&tlev=0&tseq=0&season=60&format=iCal", "Goon and Friends": "webcal://stats.sharksice.timetoscore.com/team-cal.php?team=3878&tlev=0&tseq=0&season=60&format=iCal"}, "Adult Division 5A": {"Irish Car Bombs": "webcal://stats.sharksice.timetoscore.com/team-cal.php?team=2610&tlev=0&tseq=0&season=60&format=iCal", "Nuggets 1": "webcal://stats.sharksice.timetoscore.com/team-cal.php?team=356&tlev=0&tseq=0&season=60&format=iCal", "Grizzlies": "webcal://stats.sharksice.timetoscore.com/team-cal.php?team=297&tlev=0&tseq=0&season=60&format=iCal", "French Toast": "webcal://stats.sharksice.timetoscore.com/team-cal.php?team=2257&tlev=0&tseq=0&season=60&format=iCal", "Royals 1": "webcal://stats.sharksice.timetoscore.com/team-cal.php?team=3877&tlev=0&tseq=0&season=60&format=iCal", "Cant Stop Wont Stop": "webcal://stats.sharksice.timetoscore.com/team-cal.php?team=3067&tlev=0&tseq=0&season=60&format=iCal", "Chupacabra": "webcal://stats.sharksice.timetoscore.com/team-cal.php?team=3876&tlev=0&tseq=0&season=60&format=iCal", "Blackhawks": "webcal://stats.sharksice.timetoscore.com/team-cal.php?team=4715&tlev=0&tseq=0&season=60&format=iCal", "Jets": "webcal://stats.sharksice.timetoscore.com/team-cal.php?team=841&tlev=0&tseq=0&season=60&format=iCal", "Mermen Too": "webcal://stats.sharksice.timetoscore.com/team-cal.php?team=4673&tlev=0&tseq=0&season=60&format=iCal"}, "Adult Division 5B": {"Norcal Crossover Batalion": "webcal://stats.sharksice.timetoscore.com/team-cal.php?team=3066&tlev=0&tseq=0&season=60&format=iCal", "EDWS": "webcal://stats.sharksice.timetoscore.com/team-cal.php?team=4729&tlev=0&tseq=0&season=60&format=iCal", "LinkedIn": "webcal://stats.sharksice.timetoscore.com/team-cal.php?team=2293&tlev=0&tseq=0&season=60&format=iCal", "Time Lords": "webcal://stats.sharksice.timetoscore.com/team-cal.php?team=2046&tlev=0&tseq=0&season=60&format=iCal", "Taquieria Con Carne": "webcal://stats.sharksice.timetoscore.com/team-cal.php?team=3766&tlev=0&tseq=0&season=60&format=iCal", "Mucho Macho  Muchachos": "webcal://stats.sharksice.timetoscore.com/team-cal.php?team=4185&tlev=0&tseq=0&season=60&format=iCal", "Wolverines 1": "webcal://stats.sharksice.timetoscore.com/team-cal.php?team=34&tlev=0&tseq=0&season=60&format=iCal"}, "Adult Division 6A": {"The Fruit Company": "webcal://stats.sharksice.timetoscore.com/team-cal.php?team=4612&tlev=0&tseq=0&season=60&format=iCal", "Bandits 1": "webcal://stats.sharksice.timetoscore.com/team-cal.php?team=28&tlev=0&tseq=0&season=60&format=iCal", "Hooligans": "webcal://stats.sharksice.timetoscore.com/team-cal.php?team=2062&tlev=0&tseq=0&season=60&format=iCal", "Tyrannosaurs": "webcal://stats.sharksice.timetoscore.com/team-cal.php?team=2978&tlev=0&tseq=0&season=60&format=iCal", "Peter North Stars": "webcal://stats.sharksice.timetoscore.com/team-cal.php?team=2052&tlev=0&tseq=0&season=60&format=iCal", "SJ Sofa Kings": "webcal://stats.sharksice.timetoscore.com/team-cal.php?team=4428&tlev=0&tseq=0&season=60&format=iCal", "Cereal Killers": "webcal://stats.sharksice.timetoscore.com/team-cal.php?team=306&tlev=0&tseq=0&season=60&format=iCal", "K-Wings": "webcal://stats.sharksice.timetoscore.com/team-cal.php?team=70&tlev=0&tseq=0&season=60&format=iCal", "Rangers": "webcal://stats.sharksice.timetoscore.com/team-cal.php?team=43&tlev=0&tseq=0&season=60&format=iCal", "Stampede": "webcal://stats.sharksice.timetoscore.com/team-cal.php?team=53&tlev=0&tseq=0&season=60&format=iCal", "Nuggets 2": "webcal://stats.sharksice.timetoscore.com/team-cal.php?team=1780&tlev=0&tseq=0&season=60&format=iCal", "Irish Car Bombs 2": "webcal://stats.sharksice.timetoscore.com/team-cal.php?team=2708&tlev=0&tseq=0&season=60&format=iCal", "Team America": "webcal://stats.sharksice.timetoscore.com/team-cal.php?team=2297&tlev=0&tseq=0&season=60&format=iCal", "Rogue Squadron": "webcal://stats.sharksice.timetoscore.com/team-cal.php?team=3328&tlev=0&tseq=0&season=60&format=iCal", "Kraken Beers": "webcal://stats.sharksice.timetoscore.com/team-cal.php?team=4724&tlev=0&tseq=0&season=60&format=iCal"}, "Adult Division 6B": {"Swashpucklers": "webcal://stats.sharksice.timetoscore.com/team-cal.php?team=2960&tlev=0&tseq=0&season=60&format=iCal", "Falcons": "webcal://stats.sharksice.timetoscore.com/team-cal.php?team=2963&tlev=0&tseq=0&season=60&format=iCal", "Thresher Sharks": "webcal://stats.sharksice.timetoscore.com/team-cal.php?team=2970&tlev=0&tseq=0&season=60&format=iCal", "Chiefs 1": "webcal://stats.sharksice.timetoscore.com/team-cal.php?team=806&tlev=0&tseq=0&season=60&format=iCal", "Pacific Predators": "webcal://stats.sharksice.timetoscore.com/team-cal.php?team=567&tlev=0&tseq=0&season=60&format=iCal", "Seal Team Sticks": "webcal://stats.sharksice.timetoscore.com/team-cal.php?team=4688&tlev=0&tseq=0&season=60&format=iCal", "Stanleys Closers": "webcal://stats.sharksice.timetoscore.com/team-cal.php?team=4725&tlev=0&tseq=0&season=60&format=iCal", "SJ Beer League Dev. Program": "webcal://stats.sharksice.timetoscore.com/team-cal.php?team=4812&tlev=0&tseq=0&season=60&format=iCal", "Raccoons": "webcal://stats.sharksice.timetoscore.com/team-cal.php?team=2036&tlev=0&tseq=0&season=60&format=iCal", "Blade Runners": "webcal://stats.sharksice.timetoscore.com/team-cal.php?team=46&tlev=0&tseq=0&season=60&format=iCal", "Royals 2": "webcal://stats.sharksice.timetoscore.com/team-cal.php?team=3330&tlev=0&tseq=0&season=60&format=iCal", "Leftovers": "webcal://stats.sharksice.timetoscore.com/team-cal.php?team=811&tlev=0&tseq=0&season=60&format=iCal"}, "Adult Division 7A": {"Royals 3": "webcal://stats.sharksice.timetoscore.com/team-cal.php?team=3882&tlev=0&tseq=0&season=60&format=iCal", "Bandits 2": "webcal://stats.sharksice.timetoscore.com/team-cal.php?team=19&tlev=0&tseq=0&season=60&format=iCal", "Ice Breakers": "webcal://stats.sharksice.timetoscore.com/team-cal.php?team=2063&tlev=0&tseq=0&season=60&format=iCal", "Hectors Pool Service": "webcal://stats.sharksice.timetoscore.com/team-cal.php?team=2962&tlev=0&tseq=0&season=60&format=iCal", "Irish Car Bombs 3": "webcal://stats.sharksice.timetoscore.com/team-cal.php?team=2965&tlev=0&tseq=0&season=60&format=iCal", "Red Dragons": "webcal://stats.sharksice.timetoscore.com/team-cal.php?team=1834&tlev=0&tseq=0&season=60&format=iCal", "Seal Team Sticks 2": "webcal://stats.sharksice.timetoscore.com/team-cal.php?team=4712&tlev=0&tseq=0&season=60&format=iCal", "Rebel Scum 1": "webcal://stats.sharksice.timetoscore.com/team-cal.php?team=3887&tlev=0&tseq=0&season=60&format=iCal", "CineLux Theatres": "webcal://stats.sharksice.timetoscore.com/team-cal.php?team=87&tlev=0&tseq=0&season=60&format=iCal", "Cant Score Wont Score": "webcal://stats.sharksice.timetoscore.com/team-cal.php?team=4187&tlev=0&tseq=0&season=60&format=iCal"}, "Adult Division 7B East": {"Rebel Scum 2": "webcal://stats.sharksice.timetoscore.com/team-cal.php?team=4121&tlev=0&tseq=0&season=60&format=iCal", "Cobra Kai 1": "webcal://stats.sharksice.timetoscore.com/team-cal.php?team=4716&tlev=0&tseq=0&season=60&format=iCal", "Tsunami": "webcal://stats.sharksice.timetoscore.com/team-cal.php?team=86&tlev=0&tseq=0&season=60&format=iCal", "Red Hawks": "webcal://stats.sharksice.timetoscore.com/team-cal.php?team=2714&tlev=0&tseq=0&season=60&format=iCal", "Chiefs 2": "webcal://stats.sharksice.timetoscore.com/team-cal.php?team=4613&tlev=0&tseq=0&season=60&format=iCal", "Scrubs": "webcal://stats.sharksice.timetoscore.com/team-cal.php?team=2039&tlev=0&tseq=0&season=60&format=iCal", "Schrute Farms": "webcal://stats.sharksice.timetoscore.com/team-cal.php?team=3433&tlev=0&tseq=0&season=60&format=iCal", "Team Beer": "webcal://stats.sharksice.timetoscore.com/team-cal.php?team=4637&tlev=0&tseq=0&season=60&format=iCal", "Stiflers Mom 1": "webcal://stats.sharksice.timetoscore.com/team-cal.php?team=2966&tlev=0&tseq=0&season=60&format=iCal", "OHC 2": "webcal://stats.sharksice.timetoscore.com/team-cal.php?team=299&tlev=0&tseq=0&season=60&format=iCal", "Scarebears": "webcal://stats.sharksice.timetoscore.com/team-cal.php?team=3885&tlev=0&tseq=0&season=60&format=iCal"}, "Adult Division 7B West": {"Whiskey Richards": "webcal://stats.sharksice.timetoscore.com/team-cal.php?team=4632&tlev=0&tseq=0&season=60&format=iCal", "Avengers": "webcal://stats.sharksice.timetoscore.com/team-cal.php?team=57&tlev=0&tseq=0&season=60&format=iCal", "Ravens": "webcal://stats.sharksice.timetoscore.com/team-cal.php?team=471&tlev=0&tseq=0&season=60&format=iCal", "Seal Team Sticks 3": "webcal://stats.sharksice.timetoscore.com/team-cal.php?team=4713&tlev=0&tseq=0&season=60&format=iCal", "Beaver Dragons": "webcal://stats.sharksice.timetoscore.com/team-cal.php?team=4711&tlev=0&tseq=0&season=60&format=iCal", "Skull and CrossChecks": "webcal://stats.sharksice.timetoscore.com/team-cal.php?team=4826&tlev=0&tseq=0&season=60&format=iCal", "Choking Hazards": "webcal://stats.sharksice.timetoscore.com/team-cal.php?team=3329&tlev=0&tseq=0&season=60&format=iCal", "Night Hawks 2": "webcal://stats.sharksice.timetoscore.com/team-cal.php?team=2266&tlev=0&tseq=0&season=60&format=iCal", "Buffalo Wings": "webcal://stats.sharksice.timetoscore.com/team-cal.php?team=2073&tlev=0&tseq=0&season=60&format=iCal", "Destroyers": "webcal://stats.sharksice.timetoscore.com/team-cal.php?team=879&tlev=0&tseq=0&season=60&format=iCal"}, "Adult Division 8A": {"Ice Badgers": "webcal://stats.sharksice.timetoscore.com/team-cal.php?team=4691&tlev=0&tseq=0&season=60&format=iCal", "Draggin Iceholes": "webcal://stats.sharksice.timetoscore.com/team-cal.php?team=4690&tlev=0&tseq=0&season=60&format=iCal", "Irish Car Bombs 4": "webcal://stats.sharksice.timetoscore.com/team-cal.php?team=4122&tlev=0&tseq=0&season=60&format=iCal", "Thresher Sharks 2": "webcal://stats.sharksice.timetoscore.com/team-cal.php?team=3437&tlev=0&tseq=0&season=60&format=iCal", "Cant Skate Wont Skate": "webcal://stats.sharksice.timetoscore.com/team-cal.php?team=4633&tlev=0&tseq=0&season=60&format=iCal"}, "Adult Division 8B": {"Cobra Kai 2": "webcal://stats.sharksice.timetoscore.com/team-cal.php?team=4636&tlev=0&tseq=0&season=60&format=iCal", "Night Hawks 3": "webcal://stats.sharksice.timetoscore.com/team-cal.php?team=2258&tlev=0&tseq=0&season=60&format=iCal", "Habs": "webcal://stats.sharksice.timetoscore.com/team-cal.php?team=32&tlev=0&tseq=0&season=60&format=iCal", "Rebel Scum 3": "webcal://stats.sharksice.timetoscore.com/team-cal.php?team=3769&tlev=0&tseq=0&season=60&format=iCal", "Chiefs 4": "webcal://stats.sharksice.timetoscore.com/team-cal.php?team=4615&tlev=0&tseq=0&season=60&format=iCal", "Ice Force": "webcal://stats.sharksice.timetoscore.com/team-cal.php?team=638&tlev=0&tseq=0&season=60&format=iCal", "Ice Monkeys": "webcal://stats.sharksice.timetoscore.com/team-cal.php?team=202&tlev=0&tseq=0&season=60&format=iCal", "Unhealthy Scratch": "webcal://stats.sharksice.timetoscore.com/team-cal.php?team=2606&tlev=0&tseq=0&season=60&format=iCal", "Puckaneers": "webcal://stats.sharksice.timetoscore.com/team-cal.php?team=4635&tlev=0&tseq=0&season=60&format=iCal", "Seal Team Sticks 4": "webcal://stats.sharksice.timetoscore.com/team-cal.php?team=3384&tlev=0&tseq=0&season=60&format=iCal", "Rebels": "webcal://stats.sharksice.timetoscore.com/team-cal.php?team=75&tlev=0&tseq=0&season=60&format=iCal", "Chiefs 3": "webcal://stats.sharksice.timetoscore.com/team-cal.php?team=4827&tlev=0&tseq=0&season=60&format=iCal", "EDWS 2": "webcal://stats.sharksice.timetoscore.com/team-cal.php?team=3225&tlev=0&tseq=0&season=60&format=iCal", "BK 10": "webcal://stats.sharksice.timetoscore.com/team-cal.php?team=4462&tlev=0&tseq=0&season=60&format=iCal"}, "Adult Division 9": {"Chiefs 5": "webcal://stats.sharksice.timetoscore.com/team-cal.php?team=4727&tlev=0&tseq=0&season=60&format=iCal", "Lil Puckers": "webcal://stats.sharksice.timetoscore.com/team-cal.php?team=4772&tlev=0&tseq=0&season=60&format=iCal", "JuggerNots": "webcal://stats.sharksice.timetoscore.com/team-cal.php?team=4809&tlev=0&tseq=0&season=60&format=iCal", "A-Team": "webcal://stats.sharksice.timetoscore.com/team-cal.php?team=85&tlev=0&tseq=0&season=60&format=iCal", "Rebel Scum 4": "webcal://stats.sharksice.timetoscore.com/team-cal.php?team=4810&tlev=0&tseq=0&season=60&format=iCal"}}